assemblyline_client/__init__.py
assemblyline_client/submit.py
assemblyline_client/common/__init__.py
assemblyline_client/common/classification.py
assemblyline_client/v3_client/__init__.py
assemblyline_client/v3_client/utils.py
assemblyline_client/v4_client/__init__.py
assemblyline_client/v4_client/client.py
assemblyline_client/v4_client/common/__init__.py
assemblyline_client/v4_client/common/submit_utils.py
assemblyline_client/v4_client/common/utils.py
assemblyline_client/v4_client/module/__init__.py
assemblyline_client/v4_client/module/alert.py
assemblyline_client/v4_client/module/assistant.py
assemblyline_client/v4_client/module/badlist.py
assemblyline_client/v4_client/module/bundle.py
assemblyline_client/v4_client/module/error.py
assemblyline_client/v4_client/module/file.py
assemblyline_client/v4_client/module/hash_search.py
assemblyline_client/v4_client/module/help.py
assemblyline_client/v4_client/module/heuristics.py
assemblyline_client/v4_client/module/ingest.py
assemblyline_client/v4_client/module/ontology.py
assemblyline_client/v4_client/module/replay.py
assemblyline_client/v4_client/module/result.py
assemblyline_client/v4_client/module/safelist.py
assemblyline_client/v4_client/module/service.py
assemblyline_client/v4_client/module/signature.py
assemblyline_client/v4_client/module/socketio.py
assemblyline_client/v4_client/module/submission.py
assemblyline_client/v4_client/module/submit.py
assemblyline_client/v4_client/module/system.py
assemblyline_client/v4_client/module/user.py
assemblyline_client/v4_client/module/workflow.py
assemblyline_client/v4_client/module/search/__init__.py
assemblyline_client/v4_client/module/search/facet.py
assemblyline_client/v4_client/module/search/fields.py
assemblyline_client/v4_client/module/search/grouped.py
assemblyline_client/v4_client/module/search/histogram.py
assemblyline_client/v4_client/module/search/stats.py
assemblyline_client/v4_client/module/search/stream.py
assemblyline_client-4.9.9.dist-info/licenses/LICENCE.md
assemblyline_client-4.9.9.dist-info/METADATA
assemblyline_client-4.9.9.dist-info/WHEEL
assemblyline_client-4.9.9.dist-info/entry_points.txt
assemblyline_client-4.9.9.dist-info/top_level.txt
assemblyline_client-4.9.9.dist-info/RECORD
