Metadata-Version: 2.4
Name: assemblyline-client
Version: 4.9.9
Summary: Assemblyline v4 client library
Home-page: https://github.com/CybercentreCanada/assemblyline_client
Author: CSE-CST Assemblyline development team
Author-email: assemblyline@cyber.gc.ca
License: MIT
Keywords: development assemblyline client gc canada cse-cst cse cst
Classifier: Development Status :: 5 - Production/Stable
Classifier: Intended Audience :: Developers
Classifier: Topic :: Software Development :: Libraries
Classifier: License :: OSI Approved :: MIT License
Classifier: Programming Language :: Python :: 3.6
Classifier: Programming Language :: Python :: 3.7
Classifier: Programming Language :: Python :: 3.8
Classifier: Programming Language :: Python :: 3.9
Classifier: Programming Language :: Python :: 3.10
Classifier: Programming Language :: Python :: 3.11
Classifier: Programming Language :: Python :: 3.12
License-File: LICENCE.md
Requires-Dist: pycryptodome
Requires-Dist: requests
Requires-Dist: requests[security]
Requires-Dist: python-baseconv
Requires-Dist: python-socketio[client]
Requires-Dist: socketio-client==0.5.7.4
Provides-Extra: test
Requires-Dist: pytest; extra == "test"
Requires-Dist: cart; extra == "test"
Requires-Dist: assemblyline; extra == "test"
Dynamic: author
Dynamic: author-email
Dynamic: classifier
Dynamic: description
Dynamic: description-content-type
Dynamic: home-page
Dynamic: keywords
Dynamic: license
Dynamic: license-file
Dynamic: provides-extra
Dynamic: requires-dist
Dynamic: summary
